affetch/__init__.py
affetch/__version__.py
affetch/main.py
alphafoldfetch-0.0.1.dist-info/METADATA
alphafoldfetch-0.0.1.dist-info/WHEEL
alphafoldfetch-0.0.1.dist-info/entry_points.txt
alphafoldfetch-0.0.1.dist-info/licenses/AUTHORS.md
alphafoldfetch-0.0.1.dist-info/licenses/LICENSE.txt
alphafoldfetch-0.0.1.dist-info/RECORD
