Metadata-Version: 2.3
Name: AlphaFoldFetch
Version: 0.0.1
Summary: A tool for downloading AlphaFold structures using UniProt IDs or FASTA files
Project-URL: Documentation, https://github.com/mansanlab/alphafoldfetch
Project-URL: Source, https://github.com/mansanlab/alphafoldfetch
Author-email: Edgar Manriquez-Sandoval <emanriq1@jhu.edu>
License: MIT
License-File: AUTHORS.md
License-File: LICENSE.txt
Keywords: alphafold,download,fasta,fetch,file,get
Classifier: Development Status :: 2 - Pre-Alpha
Classifier: Programming Language :: Python
Classifier: Programming Language :: Python :: 3.10
Classifier: Programming Language :: Python :: 3.11
Classifier: Programming Language :: Python :: 3.12
Classifier: Programming Language :: Python :: Implementation :: CPython
Requires-Python: >=3.10
Requires-Dist: aiohttp
Requires-Dist: asyncio
Requires-Dist: typer
